tay/__init__.py
tay/sheet.py
tay/utils.py
tay-0.1.0.dist-info/LICENSE
tay-0.1.0.dist-info/METADATA
tay-0.1.0.dist-info/WHEEL
tay-0.1.0.dist-info/RECORD
