Metadata-Version: 2.3
Name: tay
Version: 0.1.0
Summary: Python library that provides interface for table formats such as csv, xlsx 
License: MIT
Keywords: tay,csv,xlsx
Author: Gregory Bakhtin
Author-email: greasha46@gmail.com
Requires-Python: >=3.8
Classifier: License :: OSI Approved :: MIT License
Classifier: Programming Language :: Python :: 3
Classifier: Programming Language :: Python :: 3.8
Classifier: Programming Language :: Python :: 3.9
Classifier: Programming Language :: Python :: 3.10
Classifier: Programming Language :: Python :: 3.11
Classifier: Programming Language :: Python :: 3.12
Classifier: Programming Language :: Python :: 3.13
Classifier: Programming Language :: Python :: 3.7
Requires-Dist: openpyxl (==3.1.5)
Project-URL: Homepage, https://github.com/kra53n/tay
Project-URL: Repository, https://github.com/kra53n/tay
